ssapy/__init__.py
ssapy/ssapy.py
ssapy-0.0.1.dist-info/LICENSE
ssapy-0.0.1.dist-info/METADATA
ssapy-0.0.1.dist-info/WHEEL
ssapy-0.0.1.dist-info/top_level.txt
ssapy-0.0.1.dist-info/RECORD
