Metadata-Version: 2.1
Name: ssapy
Version: 0.0.1
Summary: Singular Spectrum Analysis
Author-email: Maxime Logé <max.loge@gmail.com>
Project-URL: Homepage, https://github.com/maxloge/ssapy
Project-URL: Bug Tracker, https://github.com/maxloge/ssapy/issues
Classifier: Programming Language :: Python :: 3
Classifier: License :: OSI Approved :: MIT License
Classifier: Operating System :: OS Independent
Requires-Python: >=3.7
License-File: LICENSE
